[{"id":"604988af-d2b4-4d0e-8feb-81600dbaad39","hash":"B4C+cSs5dOycubK+/6fzkUOuwoo=","counter":1,"isNew":false,"isSecondOrder":false,"type":"web.config @enableVersionHeader","level":"Low","scanMode":"Unknown","isFavorite":false,"approvalState":"None","hasJiraTicket":false,"isSuppressed":false,"isSuspected":false,"vulnerableValue":"@enableVersionHeader","issueType":"Configuration","function":"@enableVersionHeader","scanModule":"Configuration","bestPlaceToFixFile":null,"bestPlaceToFixLine":null,"entryPointFile":null,"entryPointLine":null,"sourceFile":"./WebGoat/WebGoatCoins/Web.config","sourceBeginLine":-1,"sourceEndLine":-1,"sourceBeginColumn":-1,"sourceEndColumn":-1,"vulnerableComponent":null,"vulnerableScaComponent":null,"hasAdditionalConditions":false,"language":"None"}, {"id":"34c945e9-4f41-4e7a-8a25-4446fd9c7331","hash":"HnX0VlJDAnZ05CAt3L1nI+gLgGc=","counter":2,"isNew":false,"isSecondOrder":false,"type":"web.config @viewStateEncryptionMode","level":"Low","scanMode":"Unknown","isFavorite":false,"approvalState":"None","hasJiraTicket":false,"isSuppressed":false,"isSuspected":false,"vulnerableValue":"@viewStateEncryptionMode","issueType":"Configuration","function":"@viewStateEncryptionMode","scanModule":"Configuration","bestPlaceToFixFile":null,"bestPlaceToFixLine":null,"entryPointFile":null,"entryPointLine":null,"sourceFile":"./WebGoat/WebGoatCoins/Web.config","sourceBeginLine":-1,"sourceEndLine":-1,"sourceBeginColumn":-1,"sourceEndColumn":-1,"vulnerableComponent":null,"vulnerableScaComponent":null,"hasAdditionalConditions":false,"language":"None"}, {"id":"dbf4fe37-b1db-4487-82ed-823efd703796","hash":"k7IGHh5bP5h5xmtjG4wkmHIOpwU=","counter":3,"isNew":false,"isSecondOrder":false,"type":"web.config @httpOnlyCookies","level":"Low","scanMode":"Unknown","isFavorite":false,"approvalState":"None","hasJiraTicket":false,"isSuppressed":false,"isSuspected":false,"vulnerableValue":"@httpOnlyCookies","issueType":"Configuration","function":"@httpOnlyCookies","scanModule":"Configuration","bestPlaceToFixFile":null,"bestPlaceToFixLine":null,"entryPointFile":null,"entryPointLine":null,"sourceFile":"./WebGoat/WebGoatCoins/Web.config","sourceBeginLine":-1,"sourceEndLine":-1,"sourceBeginColumn":-1,"sourceEndColumn":-1,"vulnerableComponent":null,"vulnerableScaComponent":null,"hasAdditionalConditions":false,"language":"None"}, {"id":"a73c15cf-eb15-4538-a55e-282746984da2","hash":"GUWacWD8dfLBYIUEwoHhhoDznuI=","counter":4,"isNew":false,"isSecondOrder":false,"type":"web.config @requireSSL","level":"Low","scanMode":"Unknown","isFavorite":false,"approvalState":"None","hasJiraTicket":false,"isSuppressed":false,"isSuspected":false,"vulnerableValue":"@requireSSL","issueType":"Configuration","function":"@requireSSL","scanModule":"Configuration","bestPlaceToFixFile":null,"bestPlaceToFixLine":null,"entryPointFile":null,"entryPointLine":null,"sourceFile":"./WebGoat/WebGoatCoins/Web.config","sourceBeginLine":-1,"sourceEndLine":-1,"sourceBeginColumn":-1,"sourceEndColumn":-1,"vulnerableComponent":null,"vulnerableScaComponent":null,"hasAdditionalConditions":false,"language":"None"}, {"id":"b99b3ae3-1dbd-452d-a9c9-9d86ea67c1c3","hash":"HC4280InlCqhbxIuOR6G0gZyKBU=","counter":5,"isNew":false,"isSecondOrder":false,"type":"web.config @cookieless","level":"Low","scanMode":"Unknown","isFavorite":false,"approvalState":"None","hasJiraTicket":false,"isSuppressed":false,"isSuspected":false,"vulnerableValue":"@cookieless","issueType":"Configuration","function":"@cookieless","scanModule":"Configuration","bestPlaceToFixFile":null,"bestPlaceToFixLine":null,"entryPointFile":null,"entryPointLine":null,"sourceFile":"./WebGoat/WebGoatCoins/Web.config","sourceBeginLine":-1,"sourceEndLine":-1,"sourceBeginColumn":-1,"sourceEndColumn":-1,"vulnerableComponent":null,"vulnerableScaComponent":null,"hasAdditionalConditions":false,"language":"None"}, {"id":"58041d71-2354-4393-9fb1-ff098d388bc6","hash":"H7aVTF4V3obefFQ32SrZuEBcP30=","counter":6,"isNew":false,"isSecondOrder":false,"type":"web.config @slidingExpiration","level":"Low","scanMode":"Unknown","isFavorite":false,"approvalState":"None","hasJiraTicket":false,"isSuppressed":false,"isSuspected":false,"vulnerableValue":"@slidingExpiration","issueType":"Configuration","function":"@slidingExpiration","scanModule":"Configuration","bestPlaceToFixFile":null,"bestPlaceToFixLine":null,"entryPointFile":null,"entryPointLine":null,"sourceFile":"./WebGoat/WebGoatCoins/Web.config","sourceBeginLine":-1,"sourceEndLine":-1,"sourceBeginColumn":-1,"sourceEndColumn":-1,"vulnerableComponent":null,"vulnerableScaComponent":null,"hasAdditionalConditions":false,"language":"None"}, {"id":"c33d3b79-b766-4309-8db5-ec57dc93300a","hash":"594o84uEJjNRfj5x2ch0OlHBUcM=","counter":7,"isNew":false,"isSecondOrder":false,"type":"web.config @allowOverride","level":"Low","scanMode":"Unknown","isFavorite":false,"approvalState":"None","hasJiraTicket":false,"isSuppressed":false,"isSuspected":false,"vulnerableValue":"@allowOverride","issueType":"Configuration","function":"@allowOverride","scanModule":"Configuration","bestPlaceToFixFile":null,"bestPlaceToFixLine":null,"entryPointFile":null,"entryPointLine":null,"sourceFile":"./WebGoat/WebGoatCoins/Web.config","sourceBeginLine":-1,"sourceEndLine":-1,"sourceBeginColumn":-1,"sourceEndColumn":-1,"vulnerableComponent":null,"vulnerableScaComponent":null,"hasAdditionalConditions":false,"language":"None"}, {"id":"981c34fa-51ee-4577-a3dd-ca1300a70a53","hash":"fiB6vBAKOcRUeCyCluwCD8y6ydM=","counter":8,"isNew":false,"isSecondOrder":false,"type":"web.config @requireSSL[@authentication]","level":"Low","scanMode":"Unknown","isFavorite":false,"approvalState":"None","hasJiraTicket":false,"isSuppressed":false,"isSuspected":false,"vulnerableValue":"@requireSSL","issueType":"Configuration","function":"@requireSSL","scanModule":"Configuration","bestPlaceToFixFile":null,"bestPlaceToFixLine":null,"entryPointFile":null,"entryPointLine":null,"sourceFile":"./WebGoat/WebGoatCoins/Web.config","sourceBeginLine":-1,"sourceEndLine":-1,"sourceBeginColumn":-1,"sourceEndColumn":-1,"vulnerableComponent":null,"vulnerableScaComponent":null,"hasAdditionalConditions":false,"language":"None"}, {"id":"fa8d29de-a9cd-4b28-97d3-c5c716f10f0e","hash":"A3jtJYAtGydX8wflTIbQVfKPcpY=","counter":9,"isNew":false,"isSecondOrder":false,"type":"web.config @statusCode","level":"Low","scanMode":"Unknown","isFavorite":false,"approvalState":"None","hasJiraTicket":false,"isSuppressed":false,"isSuspected":false,"vulnerableValue":"@statusCode","issueType":"Configuration","function":"@statusCode","scanModule":"Configuration","bestPlaceToFixFile":null,"bestPlaceToFixLine":null,"entryPointFile":null,"entryPointLine":null,"sourceFile":"./WebGoat/WebGoatCoins/Web.config","sourceBeginLine":-1,"sourceEndLine":-1,"sourceBeginColumn":-1,"sourceEndColumn":-1,"vulnerableComponent":null,"vulnerableScaComponent":null,"hasAdditionalConditions":false,"language":"None"}, {"id":"940cea6d-8175-4fe7-a6b1-2a88958bbca4","hash":"zjbDdYq5HNdZUiI5+Hg+LCpcRTc=","counter":10,"isNew":false,"isSecondOrder":false,"type":"web.config @statusCode","level":"Low","scanMode":"Unknown","isFavorite":false,"approvalState":"None","hasJiraTicket":false,"isSuppressed":false,"isSuspected":false,"vulnerableValue":"@statusCode","issueType":"Configuration","function":"@statusCode","scanModule":"Configuration","bestPlaceToFixFile":null,"bestPlaceToFixLine":null,"entryPointFile":null,"entryPointLine":null,"sourceFile":"./WebGoat/WebGoatCoins/Web.config","sourceBeginLine":-1,"sourceEndLine":-1,"sourceBeginColumn":-1,"sourceEndColumn":-1,"vulnerableComponent":null,"vulnerableScaComponent":null,"hasAdditionalConditions":false,"language":"None"}, {"id":"020aa3e6-1225-4c8a-9e4b-364049897473","hash":"Qi+a8fwrfGTH+JG6Msycmuu+1tw=","counter":11,"isNew":false,"isSecondOrder":false,"type":"web.config @statusCode","level":"Low","scanMode":"Unknown","isFavorite":false,"approvalState":"None","hasJiraTicket":false,"isSuppressed":false,"isSuspected":false,"vulnerableValue":"@statusCode","issueType":"Configuration","function":"@statusCode","scanModule":"Configuration","bestPlaceToFixFile":null,"bestPlaceToFixLine":null,"entryPointFile":null,"entryPointLine":null,"sourceFile":"./WebGoat/WebGoatCoins/Web.config","sourceBeginLine":-1,"sourceEndLine":-1,"sourceBeginColumn":-1,"sourceEndColumn":-1,"vulnerableComponent":null,"vulnerableScaComponent":null,"hasAdditionalConditions":false,"language":"None"}, {"id":"1209d47c-ff94-4ed0-998f-1966244fc77e","hash":"sKlO3IABjwL4e8LXLE5VzAMSJcg=","counter":12,"isNew":false,"isSecondOrder":false,"type":"web.config @statusCode","level":"Low","scanMode":"Unknown","isFavorite":false,"approvalState":"None","hasJiraTicket":false,"isSuppressed":false,"isSuspected":false,"vulnerableValue":"@statusCode","issueType":"Configuration","function":"@statusCode","scanModule":"Configuration","bestPlaceToFixFile":null,"bestPlaceToFixLine":null,"entryPointFile":null,"entryPointLine":null,"sourceFile":"./WebGoat/WebGoatCoins/Web.config","sourceBeginLine":-1,"sourceEndLine":-1,"sourceBeginColumn":-1,"sourceEndColumn":-1,"vulnerableComponent":null,"vulnerableScaComponent":null,"hasAdditionalConditions":false,"language":"None"}, {"id":"8a6df258-346e-45c3-a845-35d512d64c8f","hash":"dilkE9heHwVWSBsubzxqudMtetw=","counter":13,"isNew":false,"isSecondOrder":false,"type":"web.config @statusCode","level":"Low","scanMode":"Unknown","isFavorite":false,"approvalState":"None","hasJiraTicket":false,"isSuppressed":false,"isSuspected":false,"vulnerableValue":"@statusCode","issueType":"Configuration","function":"@statusCode","scanModule":"Configuration","bestPlaceToFixFile":null,"bestPlaceToFixLine":null,"entryPointFile":null,"entryPointLine":null,"sourceFile":"./WebGoat/WebGoatCoins/Web.config","sourceBeginLine":-1,"sourceEndLine":-1,"sourceBeginColumn":-1,"sourceEndColumn":-1,"vulnerableComponent":null,"vulnerableScaComponent":null,"hasAdditionalConditions":false,"language":"None"}, {"id":"023d2bc5-6098-4e25-990a-a99f47f89fac","hash":"AYf2dQWNcbn98KC+GvLMbRbtDo8=","counter":14,"isNew":false,"isSecondOrder":false,"type":"web.config @statusCode","level":"Low","scanMode":"Unknown","isFavorite":false,"approvalState":"None","hasJiraTicket":false,"isSuppressed":false,"isSuspected":false,"vulnerableValue":"@statusCode","issueType":"Configuration","function":"@statusCode","scanModule":"Configuration","bestPlaceToFixFile":null,"bestPlaceToFixLine":null,"entryPointFile":null,"entryPointLine":null,"sourceFile":"./WebGoat/WebGoatCoins/Web.config","sourceBeginLine":-1,"sourceEndLine":-1,"sourceBeginColumn":-1,"sourceEndColumn":-1,"vulnerableComponent":null,"vulnerableScaComponent":null,"hasAdditionalConditions":false,"language":"None"}, {"id":"bb3e5598-48cd-4b1c-a2d6-f53fea6933bb","hash":"II9GrLBI0EUHyRYyVqLQrHuptyc=","counter":15,"isNew":false,"isSecondOrder":false,"type":"web.config @statusCode","level":"Low","scanMode":"Unknown","isFavorite":false,"approvalState":"None","hasJiraTicket":false,"isSuppressed":false,"isSuspected":false,"vulnerableValue":"@statusCode","issueType":"Configuration","function":"@statusCode","scanModule":"Configuration","bestPlaceToFixFile":null,"bestPlaceToFixLine":null,"entryPointFile":null,"entryPointLine":null,"sourceFile":"./WebGoat/WebGoatCoins/Web.config","sourceBeginLine":-1,"sourceEndLine":-1,"sourceBeginColumn":-1,"sourceEndColumn":-1,"vulnerableComponent":null,"vulnerableScaComponent":null,"hasAdditionalConditions":false,"language":"None"}, {"id":"06327617-edb4-45ae-9f06-f970484cc2fa","hash":"HgohzdNrnv/k1m69noDN5ZHqvqE=","counter":16,"isNew":false,"isSecondOrder":false,"type":"web.config @statusCode","level":"Low","scanMode":"Unknown","isFavorite":false,"approvalState":"None","hasJiraTicket":false,"isSuppressed":false,"isSuspected":false,"vulnerableValue":"@statusCode","issueType":"Configuration","function":"@statusCode","scanModule":"Configuration","bestPlaceToFixFile":null,"bestPlaceToFixLine":null,"entryPointFile":null,"entryPointLine":null,"sourceFile":"./WebGoat/WebGoatCoins/Web.config","sourceBeginLine":-1,"sourceEndLine":-1,"sourceBeginColumn":-1,"sourceEndColumn":-1,"vulnerableComponent":null,"vulnerableScaComponent":null,"hasAdditionalConditions":false,"language":"None"}, {"id":"1bab0a87-9661-474e-970a-62878bce22fc","hash":"ztPs84ezA/YrDAQ3Mw8sEkFBDTY=","counter":17,"isNew":false,"isSecondOrder":false,"type":"web.config @statusCode","level":"Low","scanMode":"Unknown","isFavorite":false,"approvalState":"None","hasJiraTicket":false,"isSuppressed":false,"isSuspected":false,"vulnerableValue":"@statusCode","issueType":"Configuration","function":"@statusCode","scanModule":"Configuration","bestPlaceToFixFile":null,"bestPlaceToFixLine":null,"entryPointFile":null,"entryPointLine":null,"sourceFile":"./WebGoat/WebGoatCoins/Web.config","sourceBeginLine":-1,"sourceEndLine":-1,"sourceBeginColumn":-1,"sourceEndColumn":-1,"vulnerableComponent":null,"vulnerableScaComponent":null,"hasAdditionalConditions":false,"language":"None"}, {"id":"c0b06d78-d705-4e26-a326-341a65f3958d","hash":"bA+pnR+pzMYavSMev4fiymLTMvQ=","counter":18,"isNew":false,"isSecondOrder":false,"type":"web.config @statusCode","level":"Low","scanMode":"Unknown","isFavorite":false,"approvalState":"None","hasJiraTicket":false,"isSuppressed":false,"isSuspected":false,"vulnerableValue":"@statusCode","issueType":"Configuration","function":"@statusCode","scanModule":"Configuration","bestPlaceToFixFile":null,"bestPlaceToFixLine":null,"entryPointFile":null,"entryPointLine":null,"sourceFile":"./WebGoat/WebGoatCoins/Web.config","sourceBeginLine":-1,"sourceEndLine":-1,"sourceBeginColumn":-1,"sourceEndColumn":-1,"vulnerableComponent":null,"vulnerableScaComponent":null,"hasAdditionalConditions":false,"language":"None"}, {"id":"d1c439e9-f6a8-436d-a31f-2af19b24b9ff","hash":"7r1Uv0kOUH5Sf+afPJpLixLb2A8=","counter":19,"isNew":false,"isSecondOrder":false,"type":"web.config @statusCode","level":"Low","scanMode":"Unknown","isFavorite":false,"approvalState":"None","hasJiraTicket":false,"isSuppressed":false,"isSuspected":false,"vulnerableValue":"@statusCode","issueType":"Configuration","function":"@statusCode","scanModule":"Configuration","bestPlaceToFixFile":null,"bestPlaceToFixLine":null,"entryPointFile":null,"entryPointLine":null,"sourceFile":"./WebGoat/WebGoatCoins/Web.config","sourceBeginLine":-1,"sourceEndLine":-1,"sourceBeginColumn":-1,"sourceEndColumn":-1,"vulnerableComponent":null,"vulnerableScaComponent":null,"hasAdditionalConditions":false,"language":"None"}, {"id":"3386f632-89ab-43f8-849f-dce2cebd8346","hash":"sOsa7E7ZQQY73Zb6Zl8wJ4R+3bU=","counter":20,"isNew":false,"isSecondOrder":false,"type":"web.config @statusCode","level":"Low","scanMode":"Unknown","isFavorite":false,"approvalState":"None","hasJiraTicket":false,"isSuppressed":false,"isSuspected":false,"vulnerableValue":"@statusCode","issueType":"Configuration","function":"@statusCode","scanModule":"Configuration","bestPlaceToFixFile":null,"bestPlaceToFixLine":null,"entryPointFile":null,"entryPointLine":null,"sourceFile":"./WebGoat/WebGoatCoins/Web.config","sourceBeginLine":-1,"sourceEndLine":-1,"sourceBeginColumn":-1,"sourceEndColumn":-1,"vulnerableComponent":null,"vulnerableScaComponent":null,"hasAdditionalConditions":false,"language":"None"}, {"id":"934e8c5c-8f6f-468b-962a-0a135a5238da","hash":"xdf749BoL35AfTGgU0/3ylmLwrQ=","counter":21,"isNew":false,"isSecondOrder":false,"type":"web.config @statusCode","level":"Low","scanMode":"Unknown","isFavorite":false,"approvalState":"None","hasJiraTicket":false,"isSuppressed":false,"isSuspected":false,"vulnerableValue":"@statusCode","issueType":"Configuration","function":"@statusCode","scanModule":"Configuration","bestPlaceToFixFile":null,"bestPlaceToFixLine":null,"entryPointFile":null,"entryPointLine":null,"sourceFile":"./WebGoat/WebGoatCoins/Web.config","sourceBeginLine":-1,"sourceEndLine":-1,"sourceBeginColumn":-1,"sourceEndColumn":-1,"vulnerableComponent":null,"vulnerableScaComponent":null,"hasAdditionalConditions":false,"language":"None"}, {"id":"56a1ee27-cc8e-4c4e-8f10-68f413fab6b9","hash":"cJUJm85gDwXkgYJ8YnUD7wuPX3c=","counter":22,"isNew":false,"isSecondOrder":false,"type":"web.config @type","level":"Low","scanMode":"Unknown","isFavorite":false,"approvalState":"None","hasJiraTicket":false,"isSuppressed":false,"isSuspected":false,"vulnerableValue":"@type","issueType":"Configuration","function":"@type","scanModule":"Configuration","bestPlaceToFixFile":null,"bestPlaceToFixLine":null,"entryPointFile":null,"entryPointLine":null,"sourceFile":"./WebGoat/WebGoatCoins/Web.config","sourceBeginLine":-1,"sourceEndLine":-1,"sourceBeginColumn":-1,"sourceEndColumn":-1,"vulnerableComponent":null,"vulnerableScaComponent":null,"hasAdditionalConditions":false,"language":"None"}, {"id":"11728c30-ff40-40e6-b3c0-adac1f81ba4a","hash":"U9o4Q/U5uhCpqXJ437SBhFLqZWc=","counter":23,"isNew":false,"isSecondOrder":false,"type":"web.config @value[X-Frame-Options]","level":"Low","scanMode":"Unknown","isFavorite":false,"approvalState":"None","hasJiraTicket":false,"isSuppressed":false,"isSuspected":false,"vulnerableValue":"@value","issueType":"Configuration","function":"@value","scanModule":"Configuration","bestPlaceToFixFile":null,"bestPlaceToFixLine":null,"entryPointFile":null,"entryPointLine":null,"sourceFile":"./WebGoat/WebGoatCoins/Web.config","sourceBeginLine":-1,"sourceEndLine":-1,"sourceBeginColumn":-1,"sourceEndColumn":-1,"vulnerableComponent":null,"vulnerableScaComponent":null,"hasAdditionalConditions":false,"language":"None"}, {"id":"b11962cf-b852-41c0-bda6-6340ef54aef9","hash":"u5DiTIZXeuP+kT6YYAlBupAH4Rg=","counter":24,"isNew":false,"isSecondOrder":false,"type":"web.config remove/@name[X-Powered-By]","level":"Low","scanMode":"Unknown","isFavorite":false,"approvalState":"None","hasJiraTicket":false,"isSuppressed":false,"isSuspected":false,"vulnerableValue":"remove/@name","issueType":"Configuration","function":"remove/@name","scanModule":"Configuration","bestPlaceToFixFile":null,"bestPlaceToFixLine":null,"entryPointFile":null,"entryPointLine":null,"sourceFile":"./WebGoat/WebGoatCoins/Web.config","sourceBeginLine":-1,"sourceEndLine":-1,"sourceBeginColumn":-1,"sourceEndColumn":-1,"vulnerableComponent":null,"vulnerableScaComponent":null,"hasAdditionalConditions":false,"language":"None"}, {"id":"c251d20c-74bf-4f58-9b3c-b618bebbb1a1","hash":"gynSxTsx49mzaeO2qSN/+7iTivA=","counter":25,"isNew":false,"isSecondOrder":false,"type":"web.config remove/@name[Documentation]","level":"Low","scanMode":"Unknown","isFavorite":false,"approvalState":"None","hasJiraTicket":false,"isSuppressed":false,"isSuspected":false,"vulnerableValue":"remove/@name","issueType":"Configuration","function":"remove/@name","scanModule":"Configuration","bestPlaceToFixFile":null,"bestPlaceToFixLine":null,"entryPointFile":null,"entryPointLine":null,"sourceFile":"./WebGoat/WebGoatCoins/Web.config","sourceBeginLine":-1,"sourceEndLine":-1,"sourceBeginColumn":-1,"sourceEndColumn":-1,"vulnerableComponent":null,"vulnerableScaComponent":null,"hasAdditionalConditions":false,"language":"None"}, {"id":"44fab7f8-277c-4fcf-918d-55cb46bd41fa","hash":"xMEQ09oyPZ0mBdzF25M3ieu/Mp8=","counter":26,"isNew":false,"isSecondOrder":false,"type":"web.config @debug","level":"Low","scanMode":"Unknown","isFavorite":false,"approvalState":"None","hasJiraTicket":false,"isSuppressed":false,"isSuspected":false,"vulnerableValue":"@debug","issueType":"Configuration","function":"@debug","scanModule":"Configuration","bestPlaceToFixFile":null,"bestPlaceToFixLine":null,"entryPointFile":null,"entryPointLine":null,"sourceFile":"./WebGoat/Web.config","sourceBeginLine":46,"sourceEndLine":-1,"sourceBeginColumn":-1,"sourceEndColumn":-1,"vulnerableComponent":null,"vulnerableScaComponent":null,"hasAdditionalConditions":false,"language":"None"}, {"id":"132d1002-1354-4eda-add3-53aa63a51001","hash":"daloplKW3QDimLLzSbNX0qUbs2U=","counter":27,"isNew":false,"isSecondOrder":false,"type":"web.config @enableHeaderChecking","level":"Low","scanMode":"Unknown","isFavorite":false,"approvalState":"None","hasJiraTicket":false,"isSuppressed":false,"isSuspected":false,"vulnerableValue":"@enableHeaderChecking","issueType":"Configuration","function":"@enableHeaderChecking","scanModule":"Configuration","bestPlaceToFixFile":null,"bestPlaceToFixLine":null,"entryPointFile":null,"entryPointLine":null,"sourceFile":"./WebGoat/Web.config","sourceBeginLine":43,"sourceEndLine":-1,"sourceBeginColumn":-1,"sourceEndColumn":-1,"vulnerableComponent":null,"vulnerableScaComponent":null,"hasAdditionalConditions":false,"language":"None"}, {"id":"75050122-7028-4d86-861a-8e0733888e23","hash":"5ovWK822HOUDd3Rv8W8vTlHR9U8=","counter":28,"isNew":false,"isSecondOrder":false,"type":"web.config @enableVersionHeader","level":"Low","scanMode":"Unknown","isFavorite":false,"approvalState":"None","hasJiraTicket":false,"isSuppressed":false,"isSuspected":false,"vulnerableValue":"@enableVersionHeader","issueType":"Configuration","function":"@enableVersionHeader","scanModule":"Configuration","bestPlaceToFixFile":null,"bestPlaceToFixLine":null,"entryPointFile":null,"entryPointLine":null,"sourceFile":"./WebGoat/Web.config","sourceBeginLine":-1,"sourceEndLine":-1,"sourceBeginColumn":-1,"sourceEndColumn":-1,"vulnerableComponent":null,"vulnerableScaComponent":null,"hasAdditionalConditions":false,"language":"None"}, {"id":"e9ffa22c-ce69-4f31-8390-3f916e5f8744","hash":"g8R0SMwKBRkX/XfzEOOnDff3tXg=","counter":29,"isNew":false,"isSecondOrder":false,"type":"web.config @mode","level":"Low","scanMode":"Unknown","isFavorite":false,"approvalState":"None","hasJiraTicket":false,"isSuppressed":false,"isSuspected":false,"vulnerableValue":"@mode","issueType":"Configuration","function":"@mode","scanModule":"Configuration","bestPlaceToFixFile":null,"bestPlaceToFixLine":null,"entryPointFile":null,"entryPointLine":null,"sourceFile":"./WebGoat/Web.config","sourceBeginLine":53,"sourceEndLine":-1,"sourceBeginColumn":-1,"sourceEndColumn":-1,"vulnerableComponent":null,"vulnerableScaComponent":null,"hasAdditionalConditions":false,"language":"None"}, {"id":"ca94d623-b585-4b05-a517-e3852d0f8678","hash":"Z7dOMstJpvZnnqOXUtdMphU56x0=","counter":30,"isNew":false,"isSecondOrder":false,"type":"web.config @viewStateEncryptionMode","level":"Low","scanMode":"Unknown","isFavorite":false,"approvalState":"None","hasJiraTicket":false,"isSuppressed":false,"isSuspected":false,"vulnerableValue":"@viewStateEncryptionMode","issueType":"Configuration","function":"@viewStateEncryptionMode","scanModule":"Configuration","bestPlaceToFixFile":null,"bestPlaceToFixLine":null,"entryPointFile":null,"entryPointLine":null,"sourceFile":"./WebGoat/Web.config","sourceBeginLine":-1,"sourceEndLine":-1,"sourceBeginColumn":-1,"sourceEndColumn":-1,"vulnerableComponent":null,"vulnerableScaComponent":null,"hasAdditionalConditions":false,"language":"None"}, {"id":"0b89ff25-cf91-41b3-bc6a-5ecf705b83c2","hash":"+tmhPQndqcqeFx/UL3pgi54yfj0=","counter":31,"isNew":false,"isSecondOrder":false,"type":"web.config @httpOnlyCookies","level":"Low","scanMode":"Unknown","isFavorite":false,"approvalState":"None","hasJiraTicket":false,"isSuppressed":false,"isSuspected":false,"vulnerableValue":"@httpOnlyCookies","issueType":"Configuration","function":"@httpOnlyCookies","scanModule":"Configuration","bestPlaceToFixFile":null,"bestPlaceToFixLine":null,"entryPointFile":null,"entryPointLine":null,"sourceFile":"./WebGoat/Web.config","sourceBeginLine":45,"sourceEndLine":-1,"sourceBeginColumn":-1,"sourceEndColumn":-1,"vulnerableComponent":null,"vulnerableScaComponent":null,"hasAdditionalConditions":false,"language":"None"}, {"id":"d01726ef-bcef-4aa6-9653-0eae7370082c","hash":"diLOrCTbqNgmiqQXbIZFuYXGYtQ=","counter":32,"isNew":false,"isSecondOrder":false,"type":"web.config @requireSSL","level":"Low","scanMode":"Unknown","isFavorite":false,"approvalState":"None","hasJiraTicket":false,"isSuppressed":false,"isSuspected":false,"vulnerableValue":"@requireSSL","issueType":"Configuration","function":"@requireSSL","scanModule":"Configuration","bestPlaceToFixFile":null,"bestPlaceToFixLine":null,"entryPointFile":null,"entryPointLine":null,"sourceFile":"./WebGoat/Web.config","sourceBeginLine":45,"sourceEndLine":-1,"sourceBeginColumn":-1,"sourceEndColumn":-1,"vulnerableComponent":null,"vulnerableScaComponent":null,"hasAdditionalConditions":false,"language":"None"}, {"id":"7def1d25-e1fb-4ddd-9731-1fa93a7ca3ae","hash":"lj0OwLX9x7Y3iC4O+Hv8WAPPEUs=","counter":33,"isNew":false,"isSecondOrder":false,"type":"web.config @passwordFormat","level":"Low","scanMode":"Unknown","isFavorite":false,"approvalState":"None","hasJiraTicket":false,"isSuppressed":false,"isSuspected":false,"vulnerableValue":"@passwordFormat","issueType":"Configuration","function":"@passwordFormat","scanModule":"Configuration","bestPlaceToFixFile":null,"bestPlaceToFixLine":null,"entryPointFile":null,"entryPointLine":null,"sourceFile":"./WebGoat/Web.config","sourceBeginLine":57,"sourceEndLine":-1,"sourceBeginColumn":-1,"sourceEndColumn":-1,"vulnerableComponent":null,"vulnerableScaComponent":null,"hasAdditionalConditions":false,"language":"None"}, {"id":"4aa8edfd-0c8c-48b9-a58a-2e81c05b1844","hash":"cLBT+UJxlaPGknaTGpBV2yKgDxY=","counter":34,"isNew":false,"isSecondOrder":false,"type":"web.config @cookieless","level":"Low","scanMode":"Unknown","isFavorite":false,"approvalState":"None","hasJiraTicket":false,"isSuppressed":false,"isSuspected":false,"vulnerableValue":"@cookieless","issueType":"Configuration","function":"@cookieless","scanModule":"Configuration","bestPlaceToFixFile":null,"bestPlaceToFixLine":null,"entryPointFile":null,"entryPointLine":null,"sourceFile":"./WebGoat/Web.config","sourceBeginLine":-1,"sourceEndLine":-1,"sourceBeginColumn":-1,"sourceEndColumn":-1,"vulnerableComponent":null,"vulnerableScaComponent":null,"hasAdditionalConditions":false,"language":"None"}, {"id":"62723bf5-b74c-42bd-bd99-8f5ab6d4eccc","hash":"urc+znT+3eEUwGOlrWlMfqdsq0U=","counter":35,"isNew":false,"isSecondOrder":false,"type":"web.config @slidingExpiration","level":"Low","scanMode":"Unknown","isFavorite":false,"approvalState":"None","hasJiraTicket":false,"isSuppressed":false,"isSuspected":false,"vulnerableValue":"@slidingExpiration","issueType":"Configuration","function":"@slidingExpiration","scanModule":"Configuration","bestPlaceToFixFile":null,"bestPlaceToFixLine":null,"entryPointFile":null,"entryPointLine":null,"sourceFile":"./WebGoat/Web.config","sourceBeginLine":-1,"sourceEndLine":-1,"sourceBeginColumn":-1,"sourceEndColumn":-1,"vulnerableComponent":null,"vulnerableScaComponent":null,"hasAdditionalConditions":false,"language":"None"}, {"id":"ca8ad61b-9d19-42ef-9cf5-98ec99179f35","hash":"8Bmm2C9l8fB4tMo+oKfbtpOVbwU=","counter":36,"isNew":false,"isSecondOrder":false,"type":"web.config @users","level":"Low","scanMode":"Unknown","isFavorite":false,"approvalState":"None","hasJiraTicket":false,"isSuppressed":false,"isSuspected":false,"vulnerableValue":"@users","issueType":"Configuration","function":"@users","scanModule":"Configuration","bestPlaceToFixFile":null,"bestPlaceToFixLine":null,"entryPointFile":null,"entryPointLine":null,"sourceFile":"./WebGoat/Web.config","sourceBeginLine":-1,"sourceEndLine":-1,"sourceBeginColumn":-1,"sourceEndColumn":-1,"vulnerableComponent":null,"vulnerableScaComponent":null,"hasAdditionalConditions":false,"language":"None"}, {"id":"1f3dc61c-14da-4be3-81d1-82e8f7013057","hash":"4mba0WK83SM01eDkmRVyvqOGxOE=","counter":37,"isNew":false,"isSecondOrder":false,"type":"web.config @allowOverride","level":"Low","scanMode":"Unknown","isFavorite":false,"approvalState":"None","hasJiraTicket":false,"isSuppressed":false,"isSuspected":false,"vulnerableValue":"@allowOverride","issueType":"Configuration","function":"@allowOverride","scanModule":"Configuration","bestPlaceToFixFile":null,"bestPlaceToFixLine":null,"entryPointFile":null,"entryPointLine":null,"sourceFile":"./WebGoat/Web.config","sourceBeginLine":-1,"sourceEndLine":-1,"sourceBeginColumn":-1,"sourceEndColumn":-1,"vulnerableComponent":null,"vulnerableScaComponent":null,"hasAdditionalConditions":false,"language":"None"}, {"id":"97cb1cb9-5c6b-481a-b847-7379603f0bd0","hash":"YCXNTqlYQ3EAsuplhaDo39nSRaU=","counter":38,"isNew":false,"isSecondOrder":false,"type":"web.config @name[@credentials]","level":"Low","scanMode":"Unknown","isFavorite":false,"approvalState":"None","hasJiraTicket":false,"isSuppressed":false,"isSuspected":false,"vulnerableValue":"@name","issueType":"Configuration","function":"@name","scanModule":"Configuration","bestPlaceToFixFile":null,"bestPlaceToFixLine":null,"entryPointFile":null,"entryPointLine":null,"sourceFile":"./WebGoat/Web.config","sourceBeginLine":58,"sourceEndLine":-1,"sourceBeginColumn":-1,"sourceEndColumn":-1,"vulnerableComponent":null,"vulnerableScaComponent":null,"hasAdditionalConditions":false,"language":"None"}, {"id":"7affe11d-ab13-4fbe-b2dc-891b376a00e4","hash":"tJRIKja1QSMKiV/V2qmCJ1ht38c=","counter":39,"isNew":false,"isSecondOrder":false,"type":"web.config @name[@credentials]","level":"Low","scanMode":"Unknown","isFavorite":false,"approvalState":"None","hasJiraTicket":false,"isSuppressed":false,"isSuspected":false,"vulnerableValue":"@name","issueType":"Configuration","function":"@name","scanModule":"Configuration","bestPlaceToFixFile":null,"bestPlaceToFixLine":null,"entryPointFile":null,"entryPointLine":null,"sourceFile":"./WebGoat/Web.config","sourceBeginLine":59,"sourceEndLine":-1,"sourceBeginColumn":-1,"sourceEndColumn":-1,"vulnerableComponent":null,"vulnerableScaComponent":null,"hasAdditionalConditions":false,"language":"None"}, {"id":"d603f271-af1d-4886-a5a3-5435ff87127d","hash":"628mkaNqe1Rj/OfeYoQsOTjvX+s=","counter":40,"isNew":false,"isSecondOrder":false,"type":"web.config @name[@credentials]","level":"Low","scanMode":"Unknown","isFavorite":false,"approvalState":"None","hasJiraTicket":false,"isSuppressed":false,"isSuspected":false,"vulnerableValue":"@name","issueType":"Configuration","function":"@name","scanModule":"Configuration","bestPlaceToFixFile":null,"bestPlaceToFixLine":null,"entryPointFile":null,"entryPointLine":null,"sourceFile":"./WebGoat/Web.config","sourceBeginLine":60,"sourceEndLine":-1,"sourceBeginColumn":-1,"sourceEndColumn":-1,"vulnerableComponent":null,"vulnerableScaComponent":null,"hasAdditionalConditions":false,"language":"None"}, {"id":"a8b6cd0a-c2dd-4cfb-b1da-c9ce6c94ba89","hash":"KLm+Cr05b6ftoy091+8EivqQ3iI=","counter":41,"isNew":false,"isSecondOrder":false,"type":"web.config @requireSSL[@authentication]","level":"Low","scanMode":"Unknown","isFavorite":false,"approvalState":"None","hasJiraTicket":false,"isSuppressed":false,"isSuspected":false,"vulnerableValue":"@requireSSL","issueType":"Configuration","function":"@requireSSL","scanModule":"Configuration","bestPlaceToFixFile":null,"bestPlaceToFixLine":null,"entryPointFile":null,"entryPointLine":null,"sourceFile":"./WebGoat/Web.config","sourceBeginLine":56,"sourceEndLine":-1,"sourceBeginColumn":-1,"sourceEndColumn":-1,"vulnerableComponent":null,"vulnerableScaComponent":null,"hasAdditionalConditions":false,"language":"None"}, {"id":"06760aa4-1a25-4f22-8026-d33625963511","hash":"nbrxMmG2PEYa0ppbImzU23UWWBw=","counter":42,"isNew":false,"isSecondOrder":false,"type":"web.config @statusCode","level":"Low","scanMode":"Unknown","isFavorite":false,"approvalState":"None","hasJiraTicket":false,"isSuppressed":false,"isSuspected":false,"vulnerableValue":"@statusCode","issueType":"Configuration","function":"@statusCode","scanModule":"Configuration","bestPlaceToFixFile":null,"bestPlaceToFixLine":null,"entryPointFile":null,"entryPointLine":null,"sourceFile":"./WebGoat/Web.config","sourceBeginLine":-1,"sourceEndLine":-1,"sourceBeginColumn":-1,"sourceEndColumn":-1,"vulnerableComponent":null,"vulnerableScaComponent":null,"hasAdditionalConditions":false,"language":"None"}, {"id":"e46e5f34-6ab9-47d3-983c-ea15d40504c3","hash":"86kcMoYSKd6exSKgNbie8dsYtMg=","counter":43,"isNew":false,"isSecondOrder":false,"type":"web.config @statusCode","level":"Low","scanMode":"Unknown","isFavorite":false,"approvalState":"None","hasJiraTicket":false,"isSuppressed":false,"isSuspected":false,"vulnerableValue":"@statusCode","issueType":"Configuration","function":"@statusCode","scanModule":"Configuration","bestPlaceToFixFile":null,"bestPlaceToFixLine":null,"entryPointFile":null,"entryPointLine":null,"sourceFile":"./WebGoat/Web.config","sourceBeginLine":-1,"sourceEndLine":-1,"sourceBeginColumn":-1,"sourceEndColumn":-1,"vulnerableComponent":null,"vulnerableScaComponent":null,"hasAdditionalConditions":false,"language":"None"}, {"id":"58187d44-8c18-4571-bbf1-1f6e675edf51","hash":"xSRusoa+E7XrlXSRDAcaxnmgZWs=","counter":44,"isNew":false,"isSecondOrder":false,"type":"web.config @statusCode","level":"Low","scanMode":"Unknown","isFavorite":false,"approvalState":"None","hasJiraTicket":false,"isSuppressed":false,"isSuspected":false,"vulnerableValue":"@statusCode","issueType":"Configuration","function":"@statusCode","scanModule":"Configuration","bestPlaceToFixFile":null,"bestPlaceToFixLine":null,"entryPointFile":null,"entryPointLine":null,"sourceFile":"./WebGoat/Web.config","sourceBeginLine":-1,"sourceEndLine":-1,"sourceBeginColumn":-1,"sourceEndColumn":-1,"vulnerableComponent":null,"vulnerableScaComponent":null,"hasAdditionalConditions":false,"language":"None"}, {"id":"beaa7585-49f3-4ccb-b194-21894dc9c2bd","hash":"Wa9NCn6MtlObVKDigc9Jci1UMSE=","counter":45,"isNew":false,"isSecondOrder":false,"type":"web.config @statusCode","level":"Low","scanMode":"Unknown","isFavorite":false,"approvalState":"None","hasJiraTicket":false,"isSuppressed":false,"isSuspected":false,"vulnerableValue":"@statusCode","issueType":"Configuration","function":"@statusCode","scanModule":"Configuration","bestPlaceToFixFile":null,"bestPlaceToFixLine":null,"entryPointFile":null,"entryPointLine":null,"sourceFile":"./WebGoat/Web.config","sourceBeginLine":-1,"sourceEndLine":-1,"sourceBeginColumn":-1,"sourceEndColumn":-1,"vulnerableComponent":null,"vulnerableScaComponent":null,"hasAdditionalConditions":false,"language":"None"}, {"id":"080b4b32-bb74-4d89-b43c-e642053fe93a","hash":"CuFCsb7xHeVztje6w18MMEq64Po=","counter":46,"isNew":false,"isSecondOrder":false,"type":"web.config @statusCode","level":"Low","scanMode":"Unknown","isFavorite":false,"approvalState":"None","hasJiraTicket":false,"isSuppressed":false,"isSuspected":false,"vulnerableValue":"@statusCode","issueType":"Configuration","function":"@statusCode","scanModule":"Configuration","bestPlaceToFixFile":null,"bestPlaceToFixLine":null,"entryPointFile":null,"entryPointLine":null,"sourceFile":"./WebGoat/Web.config","sourceBeginLine":-1,"sourceEndLine":-1,"sourceBeginColumn":-1,"sourceEndColumn":-1,"vulnerableComponent":null,"vulnerableScaComponent":null,"hasAdditionalConditions":false,"language":"None"}, {"id":"8c373377-d1b5-4c86-8a7a-b17755481b76","hash":"1/7Z4+yrGTLpCjtyom7BAeD7sIc=","counter":47,"isNew":false,"isSecondOrder":false,"type":"web.config @statusCode","level":"Low","scanMode":"Unknown","isFavorite":false,"approvalState":"None","hasJiraTicket":false,"isSuppressed":false,"isSuspected":false,"vulnerableValue":"@statusCode","issueType":"Configuration","function":"@statusCode","scanModule":"Configuration","bestPlaceToFixFile":null,"bestPlaceToFixLine":null,"entryPointFile":null,"entryPointLine":null,"sourceFile":"./WebGoat/Web.config","sourceBeginLine":-1,"sourceEndLine":-1,"sourceBeginColumn":-1,"sourceEndColumn":-1,"vulnerableComponent":null,"vulnerableScaComponent":null,"hasAdditionalConditions":false,"language":"None"}, {"id":"f5be31dc-256c-4fa0-bcd6-73d399b5f92a","hash":"ZwW7e/2NTWZjplsSVtC+5UDJPo8=","counter":48,"isNew":false,"isSecondOrder":false,"type":"web.config @statusCode","level":"Low","scanMode":"Unknown","isFavorite":false,"approvalState":"None","hasJiraTicket":false,"isSuppressed":false,"isSuspected":false,"vulnerableValue":"@statusCode","issueType":"Configuration","function":"@statusCode","scanModule":"Configuration","bestPlaceToFixFile":null,"bestPlaceToFixLine":null,"entryPointFile":null,"entryPointLine":null,"sourceFile":"./WebGoat/Web.config","sourceBeginLine":-1,"sourceEndLine":-1,"sourceBeginColumn":-1,"sourceEndColumn":-1,"vulnerableComponent":null,"vulnerableScaComponent":null,"hasAdditionalConditions":false,"language":"None"}, {"id":"a84aceb2-5c85-4857-b459-d06d52b277b5","hash":"S+UehaGt5jLeZ2uwu6pkI/w3Ego=","counter":49,"isNew":false,"isSecondOrder":false,"type":"web.config @statusCode","level":"Low","scanMode":"Unknown","isFavorite":false,"approvalState":"None","hasJiraTicket":false,"isSuppressed":false,"isSuspected":false,"vulnerableValue":"@statusCode","issueType":"Configuration","function":"@statusCode","scanModule":"Configuration","bestPlaceToFixFile":null,"bestPlaceToFixLine":null,"entryPointFile":null,"entryPointLine":null,"sourceFile":"./WebGoat/Web.config","sourceBeginLine":-1,"sourceEndLine":-1,"sourceBeginColumn":-1,"sourceEndColumn":-1,"vulnerableComponent":null,"vulnerableScaComponent":null,"hasAdditionalConditions":false,"language":"None"}, {"id":"df520261-a280-44fb-9c17-9761b8af9743","hash":"DfShwM25DmdfrVeeNBc319QZv5w=","counter":50,"isNew":false,"isSecondOrder":false,"type":"web.config @statusCode","level":"Low","scanMode":"Unknown","isFavorite":false,"approvalState":"None","hasJiraTicket":false,"isSuppressed":false,"isSuspected":false,"vulnerableValue":"@statusCode","issueType":"Configuration","function":"@statusCode","scanModule":"Configuration","bestPlaceToFixFile":null,"bestPlaceToFixLine":null,"entryPointFile":null,"entryPointLine":null,"sourceFile":"./WebGoat/Web.config","sourceBeginLine":-1,"sourceEndLine":-1,"sourceBeginColumn":-1,"sourceEndColumn":-1,"vulnerableComponent":null,"vulnerableScaComponent":null,"hasAdditionalConditions":false,"language":"None"}, {"id":"9d163b89-1e80-4bed-82b3-d6e42703cb02","hash":"YavhrTfG9+n3ZKe0RWZ0Gpy7LDg=","counter":51,"isNew":false,"isSecondOrder":false,"type":"web.config @statusCode","level":"Low","scanMode":"Unknown","isFavorite":false,"approvalState":"None","hasJiraTicket":false,"isSuppressed":false,"isSuspected":false,"vulnerableValue":"@statusCode","issueType":"Configuration","function":"@statusCode","scanModule":"Configuration","bestPlaceToFixFile":null,"bestPlaceToFixLine":null,"entryPointFile":null,"entryPointLine":null,"sourceFile":"./WebGoat/Web.config","sourceBeginLine":-1,"sourceEndLine":-1,"sourceBeginColumn":-1,"sourceEndColumn":-1,"vulnerableComponent":null,"vulnerableScaComponent":null,"hasAdditionalConditions":false,"language":"None"}, {"id":"9b8fe343-ce78-4927-b378-d0be248aec63","hash":"pYdfxNzYdlXwji6WlCTXdYstpqA=","counter":52,"isNew":false,"isSecondOrder":false,"type":"web.config @statusCode","level":"Low","scanMode":"Unknown","isFavorite":false,"approvalState":"None","hasJiraTicket":false,"isSuppressed":false,"isSuspected":false,"vulnerableValue":"@statusCode","issueType":"Configuration","function":"@statusCode","scanModule":"Configuration","bestPlaceToFixFile":null,"bestPlaceToFixLine":null,"entryPointFile":null,"entryPointLine":null,"sourceFile":"./WebGoat/Web.config","sourceBeginLine":-1,"sourceEndLine":-1,"sourceBeginColumn":-1,"sourceEndColumn":-1,"vulnerableComponent":null,"vulnerableScaComponent":null,"hasAdditionalConditions":false,"language":"None"}, {"id":"f7d4b1b7-386e-457a-b792-8647ffd44450","hash":"vSb6UdWyfT0XcKYjPNba4WhGFss=","counter":53,"isNew":false,"isSecondOrder":false,"type":"web.config @statusCode","level":"Low","scanMode":"Unknown","isFavorite":false,"approvalState":"None","hasJiraTicket":false,"isSuppressed":false,"isSuspected":false,"vulnerableValue":"@statusCode","issueType":"Configuration","function":"@statusCode","scanModule":"Configuration","bestPlaceToFixFile":null,"bestPlaceToFixLine":null,"entryPointFile":null,"entryPointLine":null,"sourceFile":"./WebGoat/Web.config","sourceBeginLine":-1,"sourceEndLine":-1,"sourceBeginColumn":-1,"sourceEndColumn":-1,"vulnerableComponent":null,"vulnerableScaComponent":null,"hasAdditionalConditions":false,"language":"None"}, {"id":"11006fb8-4124-4b89-98c6-cedce4537158","hash":"/VsR9OcziDXez3hNQTcgfTzTN5c=","counter":54,"isNew":false,"isSecondOrder":false,"type":"web.config @statusCode","level":"Low","scanMode":"Unknown","isFavorite":false,"approvalState":"None","hasJiraTicket":false,"isSuppressed":false,"isSuspected":false,"vulnerableValue":"@statusCode","issueType":"Configuration","function":"@statusCode","scanModule":"Configuration","bestPlaceToFixFile":null,"bestPlaceToFixLine":null,"entryPointFile":null,"entryPointLine":null,"sourceFile":"./WebGoat/Web.config","sourceBeginLine":-1,"sourceEndLine":-1,"sourceBeginColumn":-1,"sourceEndColumn":-1,"vulnerableComponent":null,"vulnerableScaComponent":null,"hasAdditionalConditions":false,"language":"None"}, {"id":"690a7a09-67f8-42f1-82f6-f42c6b818f89","hash":"7BdslqaEdVrmtP+sSlguNdNxZkY=","counter":55,"isNew":false,"isSecondOrder":false,"type":"web.config @type","level":"Low","scanMode":"Unknown","isFavorite":false,"approvalState":"None","hasJiraTicket":false,"isSuppressed":false,"isSuspected":false,"vulnerableValue":"@type","issueType":"Configuration","function":"@type","scanModule":"Configuration","bestPlaceToFixFile":null,"bestPlaceToFixLine":null,"entryPointFile":null,"entryPointLine":null,"sourceFile":"./WebGoat/Web.config","sourceBeginLine":69,"sourceEndLine":-1,"sourceBeginColumn":-1,"sourceEndColumn":-1,"vulnerableComponent":null,"vulnerableScaComponent":null,"hasAdditionalConditions":false,"language":"None"}, {"id":"405aea23-87e7-4288-a230-064339726564","hash":"vNRny2+9vEhBfPC3EeFTbDA0KEc=","counter":56,"isNew":false,"isSecondOrder":false,"type":"web.config @value[X-Frame-Options]","level":"Low","scanMode":"Unknown","isFavorite":false,"approvalState":"None","hasJiraTicket":false,"isSuppressed":false,"isSuspected":false,"vulnerableValue":"@value","issueType":"Configuration","function":"@value","scanModule":"Configuration","bestPlaceToFixFile":null,"bestPlaceToFixLine":null,"entryPointFile":null,"entryPointLine":null,"sourceFile":"./WebGoat/Web.config","sourceBeginLine":-1,"sourceEndLine":-1,"sourceBeginColumn":-1,"sourceEndColumn":-1,"vulnerableComponent":null,"vulnerableScaComponent":null,"hasAdditionalConditions":false,"language":"None"}, {"id":"8d650066-223f-4c4b-9bfc-1a92627fc74a","hash":"ViJt+eA7R7ne3S+W3RzgZZTFDCE=","counter":57,"isNew":false,"isSecondOrder":false,"type":"web.config remove/@name[X-Powered-By]","level":"Low","scanMode":"Unknown","isFavorite":false,"approvalState":"None","hasJiraTicket":false,"isSuppressed":false,"isSuspected":false,"vulnerableValue":"remove/@name","issueType":"Configuration","function":"remove/@name","scanModule":"Configuration","bestPlaceToFixFile":null,"bestPlaceToFixLine":null,"entryPointFile":null,"entryPointLine":null,"sourceFile":"./WebGoat/Web.config","sourceBeginLine":-1,"sourceEndLine":-1,"sourceBeginColumn":-1,"sourceEndColumn":-1,"vulnerableComponent":null,"vulnerableScaComponent":null,"hasAdditionalConditions":false,"language":"None"}, {"id":"dc289957-96f3-4cb2-87d3-b49c8c5f8338","hash":"Y3AE50f0J7IKAdv/sYjkGGw/Rqc=","counter":58,"isNew":false,"isSecondOrder":false,"type":"web.config remove/@name[Documentation]","level":"Low","scanMode":"Unknown","isFavorite":false,"approvalState":"None","hasJiraTicket":false,"isSuppressed":false,"isSuspected":false,"vulnerableValue":"remove/@name","issueType":"Configuration","function":"remove/@name","scanModule":"Configuration","bestPlaceToFixFile":null,"bestPlaceToFixLine":null,"entryPointFile":null,"entryPointLine":null,"sourceFile":"./WebGoat/Web.config","sourceBeginLine":-1,"sourceEndLine":-1,"sourceBeginColumn":-1,"sourceEndColumn":-1,"vulnerableComponent":null,"vulnerableScaComponent":null,"hasAdditionalConditions":false,"language":"None"}]