[{"id":"8f730a3c-7a13-4b55-a084-8ad5ad9bf174","hash":"QZE84kisU2T/41yB48kjuZW8dbk=","counter":1,"isNew":true,"isSecondOrder":false,"type":"php.ini allow_url_fopen","level":"Low","scanMode":"Unknown","isFavorite":false,"approvalState":"None","hasJiraTicket":false,"isSuppressed":false,"isSuspected":false,"vulnerableValue":"allow_url_fopen","issueType":"Configuration","function":"allow_url_fopen","scanModule":"Configuration","bestPlaceToFixFile":null,"bestPlaceToFixLine":null,"entryPointFile":null,"entryPointLine":null,"sourceFile":"./php.ini","sourceBeginLine":-1,"sourceEndLine":-1,"sourceBeginColumn":-1,"sourceEndColumn":-1,"vulnerableComponent":null,"hasAdditionalConditions":false,"language":"None"}, {"id":"f3805492-6054-4914-8781-c417dd6276f2","hash":"Wj845DXsbWM6FMCXfu0QqiHtl5c=","counter":2,"isNew":true,"isSecondOrder":false,"type":"php.ini cgi.fix_pathinfo","level":"Low","scanMode":"Unknown","isFavorite":false,"approvalState":"None","hasJiraTicket":false,"isSuppressed":false,"isSuspected":false,"vulnerableValue":"cgi.fix_pathinfo","issueType":"Configuration","function":"cgi.fix_pathinfo","scanModule":"Configuration","bestPlaceToFixFile":null,"bestPlaceToFixLine":null,"entryPointFile":null,"entryPointLine":null,"sourceFile":"./php.ini","sourceBeginLine":-1,"sourceEndLine":-1,"sourceBeginColumn":-1,"sourceEndColumn":-1,"vulnerableComponent":null,"hasAdditionalConditions":false,"language":"None"}, {"id":"5cdef15e-81b1-48ca-a72a-04e71a30b792","hash":"Ti3DJp5XU+oMBM8FUuLcSA3Ab9s=","counter":3,"isNew":true,"isSecondOrder":false,"type":"php.ini display_errors","level":"Low","scanMode":"Unknown","isFavorite":false,"approvalState":"None","hasJiraTicket":false,"isSuppressed":false,"isSuspected":false,"vulnerableValue":"display_errors","issueType":"Configuration","function":"display_errors","scanModule":"Configuration","bestPlaceToFixFile":null,"bestPlaceToFixLine":null,"entryPointFile":null,"entryPointLine":null,"sourceFile":"./php.ini","sourceBeginLine":-1,"sourceEndLine":-1,"sourceBeginColumn":-1,"sourceEndColumn":-1,"vulnerableComponent":null,"hasAdditionalConditions":false,"language":"None"}, {"id":"11786c52-43a0-4cb6-871d-b8cce424e32c","hash":"oinIW4YFgm1zVZp865DsXoWY8mM=","counter":4,"isNew":true,"isSecondOrder":false,"type":"php.ini enable_dl","level":"Low","scanMode":"Unknown","isFavorite":false,"approvalState":"None","hasJiraTicket":false,"isSuppressed":false,"isSuspected":false,"vulnerableValue":"enable_dl","issueType":"Configuration","function":"enable_dl","scanModule":"Configuration","bestPlaceToFixFile":null,"bestPlaceToFixLine":null,"entryPointFile":null,"entryPointLine":null,"sourceFile":"./php.ini","sourceBeginLine":-1,"sourceEndLine":-1,"sourceBeginColumn":-1,"sourceEndColumn":-1,"vulnerableComponent":null,"hasAdditionalConditions":false,"language":"None"}, {"id":"a3ed85f9-5d9d-4689-b3ce-c5943d10f52b","hash":"INJspKDIsX2MOWhjrl7INrO8NL4=","counter":5,"isNew":true,"isSecondOrder":false,"type":"php.ini expose_php","level":"Low","scanMode":"Unknown","isFavorite":false,"approvalState":"None","hasJiraTicket":false,"isSuppressed":false,"isSuspected":false,"vulnerableValue":"expose_php","issueType":"Configuration","function":"expose_php","scanModule":"Configuration","bestPlaceToFixFile":null,"bestPlaceToFixLine":null,"entryPointFile":null,"entryPointLine":null,"sourceFile":"./php.ini","sourceBeginLine":-1,"sourceEndLine":-1,"sourceBeginColumn":-1,"sourceEndColumn":-1,"vulnerableComponent":null,"hasAdditionalConditions":false,"language":"None"}, {"id":"12860b6c-6d27-4ec6-8b16-6cacc6134e0d","hash":"AwiSI2pj3x3b43a7LsYx4IgDlSU=","counter":6,"isNew":true,"isSecondOrder":false,"type":"php.ini magic_quotes_gpc","level":"Low","scanMode":"Unknown","isFavorite":false,"approvalState":"None","hasJiraTicket":false,"isSuppressed":false,"isSuspected":false,"vulnerableValue":"magic_quotes_gpc","issueType":"Configuration","function":"magic_quotes_gpc","scanModule":"Configuration","bestPlaceToFixFile":null,"bestPlaceToFixLine":null,"entryPointFile":null,"entryPointLine":null,"sourceFile":"./php.ini","sourceBeginLine":-1,"sourceEndLine":-1,"sourceBeginColumn":-1,"sourceEndColumn":-1,"vulnerableComponent":null,"hasAdditionalConditions":false,"language":"None"}, {"id":"dae9819a-75fa-4d7e-a962-1a1d1ff89246","hash":"uj8fXU5OyDbrE5ukIt2fDc8P8b8=","counter":7,"isNew":true,"isSecondOrder":false,"type":"php.ini log_errors","level":"Low","scanMode":"Unknown","isFavorite":false,"approvalState":"None","hasJiraTicket":false,"isSuppressed":false,"isSuspected":false,"vulnerableValue":"log_errors","issueType":"Configuration","function":"log_errors","scanModule":"Configuration","bestPlaceToFixFile":null,"bestPlaceToFixLine":null,"entryPointFile":null,"entryPointLine":null,"sourceFile":"./php.ini","sourceBeginLine":-1,"sourceEndLine":-1,"sourceBeginColumn":-1,"sourceEndColumn":-1,"vulnerableComponent":null,"hasAdditionalConditions":false,"language":"None"}, {"id":"3a744ffd-3da4-4591-9fae-4c23d7a6d50f","hash":"AlwP8a6fa/TOxOWYWtQMBnqBQns=","counter":8,"isNew":true,"isSecondOrder":false,"type":"php.ini assert.active","level":"Low","scanMode":"Unknown","isFavorite":false,"approvalState":"None","hasJiraTicket":false,"isSuppressed":false,"isSuspected":false,"vulnerableValue":"assert.active","issueType":"Configuration","function":"assert.active","scanModule":"Configuration","bestPlaceToFixFile":null,"bestPlaceToFixLine":null,"entryPointFile":null,"entryPointLine":null,"sourceFile":"./php.ini","sourceBeginLine":-1,"sourceEndLine":-1,"sourceBeginColumn":-1,"sourceEndColumn":-1,"vulnerableComponent":null,"hasAdditionalConditions":false,"language":"None"}, {"id":"8d42b247-bef7-4912-8f74-9c713c4aebda","hash":"nnz4WH/ypUN9svJg4Rcw1gdsEto=","counter":9,"isNew":true,"isSecondOrder":false,"type":"php.ini max_input_time","level":"Low","scanMode":"Unknown","isFavorite":false,"approvalState":"None","hasJiraTicket":false,"isSuppressed":false,"isSuspected":false,"vulnerableValue":"max_input_time","issueType":"Configuration","function":"max_input_time","scanModule":"Configuration","bestPlaceToFixFile":null,"bestPlaceToFixLine":null,"entryPointFile":null,"entryPointLine":null,"sourceFile":"./php.ini","sourceBeginLine":-1,"sourceEndLine":-1,"sourceBeginColumn":-1,"sourceEndColumn":-1,"vulnerableComponent":null,"hasAdditionalConditions":false,"language":"None"}, {"id":"59880d17-24e0-484c-8321-413c63bf738a","hash":"GCT8fwiaQ9SxdyIGWvoADSeDw/k=","counter":10,"isNew":true,"isSecondOrder":false,"type":"php.ini open_basedir","level":"Low","scanMode":"Unknown","isFavorite":false,"approvalState":"None","hasJiraTicket":false,"isSuppressed":false,"isSuspected":false,"vulnerableValue":"open_basedir","issueType":"Configuration","function":"open_basedir","scanModule":"Configuration","bestPlaceToFixFile":null,"bestPlaceToFixLine":null,"entryPointFile":null,"entryPointLine":null,"sourceFile":"./php.ini","sourceBeginLine":-1,"sourceEndLine":-1,"sourceBeginColumn":-1,"sourceEndColumn":-1,"vulnerableComponent":null,"hasAdditionalConditions":false,"language":"None"}, {"id":"54c27af0-6e16-4741-a010-0da3be0e0902","hash":"d/v8Slbu2neK/Cjf9U/7ntQJu3Q=","counter":11,"isNew":true,"isSecondOrder":false,"type":"php.ini session.cookie_httponly","level":"Low","scanMode":"Unknown","isFavorite":false,"approvalState":"None","hasJiraTicket":false,"isSuppressed":false,"isSuspected":false,"vulnerableValue":"session.cookie_httponly","issueType":"Configuration","function":"session.cookie_httponly","scanModule":"Configuration","bestPlaceToFixFile":null,"bestPlaceToFixLine":null,"entryPointFile":null,"entryPointLine":null,"sourceFile":"./php.ini","sourceBeginLine":-1,"sourceEndLine":-1,"sourceBeginColumn":-1,"sourceEndColumn":-1,"vulnerableComponent":null,"hasAdditionalConditions":false,"language":"None"}, {"id":"35f5da28-43ca-43ed-a5a4-774f9c83cea1","hash":"IsBY9BRf4WsUb/fwo6RPATxexBI=","counter":12,"isNew":true,"isSecondOrder":false,"type":"php.ini session.save_path","level":"Low","scanMode":"Unknown","isFavorite":false,"approvalState":"None","hasJiraTicket":false,"isSuppressed":false,"isSuspected":false,"vulnerableValue":"session.save_path","issueType":"Configuration","function":"session.save_path","scanModule":"Configuration","bestPlaceToFixFile":null,"bestPlaceToFixLine":null,"entryPointFile":null,"entryPointLine":null,"sourceFile":"./php.ini","sourceBeginLine":-1,"sourceEndLine":-1,"sourceBeginColumn":-1,"sourceEndColumn":-1,"vulnerableComponent":null,"hasAdditionalConditions":false,"language":"None"}, {"id":"6bb52fcf-5339-453f-a82d-971a06c765ca","hash":"SVcqZg8+ZvJVkZvkFFGHjMz2ToI=","counter":13,"isNew":true,"isSecondOrder":false,"type":"php.ini session.use_strict_mode","level":"Low","scanMode":"Unknown","isFavorite":false,"approvalState":"None","hasJiraTicket":false,"isSuppressed":false,"isSuspected":false,"vulnerableValue":"session.use_strict_mode","issueType":"Configuration","function":"session.use_strict_mode","scanModule":"Configuration","bestPlaceToFixFile":null,"bestPlaceToFixLine":null,"entryPointFile":null,"entryPointLine":null,"sourceFile":"./php.ini","sourceBeginLine":-1,"sourceEndLine":-1,"sourceBeginColumn":-1,"sourceEndColumn":-1,"vulnerableComponent":null,"hasAdditionalConditions":false,"language":"None"}, {"id":"ad67f2ca-1204-4ad0-b098-4f6a56d8f7c4","hash":"wJG7B7qDMXLbiBWOrbygOhurkWI=","counter":14,"isNew":true,"isSecondOrder":false,"type":"Hardcoded Password PM","level":"Potential","scanMode":"Unknown","isFavorite":false,"approvalState":"None","hasJiraTicket":false,"isSuppressed":false,"isSuspected":false,"vulnerableValue":"$password = 'P@ssw0rd'","issueType":"Weakness","function":null,"scanModule":"PatternMatching","bestPlaceToFixFile":null,"bestPlaceToFixLine":null,"entryPointFile":null,"entryPointLine":null,"sourceFile":"./misc.php","sourceBeginLine":2,"sourceEndLine":2,"sourceBeginColumn":5,"sourceEndColumn":27,"vulnerableComponent":null,"hasAdditionalConditions":false,"language":"Php"}, {"id":"77bbc7cd-dc55-4b25-9b6e-dc052a207f5b","hash":"TgUcJSbVM/9TFk0AXOPkt82fe7w=","counter":15,"isNew":true,"isSecondOrder":false,"type":"php.ini session.cookie_secure","level":"Low","scanMode":"Unknown","isFavorite":false,"approvalState":"None","hasJiraTicket":false,"isSuppressed":false,"isSuspected":false,"vulnerableValue":"session.cookie_secure","issueType":"Configuration","function":"session.cookie_secure","scanModule":"Configuration","bestPlaceToFixFile":null,"bestPlaceToFixLine":null,"entryPointFile":null,"entryPointLine":null,"sourceFile":"./php.ini","sourceBeginLine":-1,"sourceEndLine":-1,"sourceBeginColumn":-1,"sourceEndColumn":-1,"vulnerableComponent":null,"hasAdditionalConditions":false,"language":"None"}, {"id":"b302722f-920e-4ea0-8e6b-1d61c28e802e","hash":"4tXhzAHVygx9PvRba6ArjvUvb54=","counter":16,"isNew":true,"isSecondOrder":false,"type":"php.ini disable_functions","level":"Low","scanMode":"Unknown","isFavorite":false,"approvalState":"None","hasJiraTicket":false,"isSuppressed":false,"isSuspected":false,"vulnerableValue":"disable_functions","issueType":"Configuration","function":"disable_functions","scanModule":"Configuration","bestPlaceToFixFile":null,"bestPlaceToFixLine":null,"entryPointFile":null,"entryPointLine":null,"sourceFile":"./php.ini","sourceBeginLine":-1,"sourceEndLine":-1,"sourceBeginColumn":-1,"sourceEndColumn":-1,"vulnerableComponent":null,"hasAdditionalConditions":false,"language":"None"}]